flextask/__main__.py
flextask/cli.py
flextask/net.py
flextask-0.0.5.dist-info/METADATA
flextask-0.0.5.dist-info/WHEEL
flextask-0.0.5.dist-info/entry_points.txt
flextask-0.0.5.dist-info/top_level.txt
flextask-0.0.5.dist-info/RECORD
