Metadata-Version: 2.1
Name: flextask
Version: 0.0.5
Summary: Flex Task CLI
Author: Grigori Fursin
License: Apache 2.0
Keywords: cmx,flextask,ft
Classifier: License :: OSI Approved :: Apache Software License
Classifier: Operating System :: OS Independent
Classifier: Programming Language :: Python :: 3.8
Classifier: Programming Language :: Python :: 3.9
Classifier: Programming Language :: Python :: 3.10
Classifier: Programming Language :: Python :: 3.11
Classifier: Programming Language :: Python :: 3.12
Requires-Python: >=3.8
Requires-Dist: setuptools
Requires-Dist: cmind
